MANIFEST.in
README.rst
setup.py
statvent/__init__.py
statvent/stats.py
statvent/web.py
statvent.egg-info/PKG-INFO
statvent.egg-info/SOURCES.txt
statvent.egg-info/dependency_links.txt
statvent.egg-info/top_level.txt