Metadata-Version: 1.0
Name: statvent
Version: 1.0.1
Summary: A simple library that writes stats about your program to a named pipe.
Home-page: https://github.com/dowski/statvent/
Author: Christian Wyglendowski
Author-email: christian@dowski.com
License: BSD
Keywords: monitoring stats statistics counters pipe
Platform: UNKNOWN
Classifier: Development Status :: 5 - Production/Stable
Classifier: Environment :: Console
Classifier: Intended Audience :: Developers
Classifier: Intended Audience :: System Administrators
Classifier: License :: OSI Approved :: BSD License
Classifier: Operating System :: POSIX :: Linux
Classifier: Operating System :: MacOS :: MacOS X
Classifier: Programming Language :: Python :: 2.6
Classifier: Programming Language :: Python :: 2.7
Classifier: Programming Language :: C
Classifier: Topic :: Software Development :: Libraries
Classifier: Topic :: System :: Monitoring
